<?xml version="1.0" encoding="utf-8"?>
<!DOCTYPE hibernate-mapping PUBLIC "-//Hibernate/Hibernate Mapping DTD 3.0//EN"
"http://www.hibernate.org/dtd/hibernate-mapping-3.0.dtd">
<!-- 
    Mapping file autogenerated by MyEclipse Persistence Tools
-->
<hibernate-mapping>
    <class name="com.imudges.meike.bean.StudentUsersChooseclass" table="`student users chooseclass`" catalog="meike">
        <composite-id name="id" class="com.imudges.meike.bean.StudentUsersChooseclassId">
            <key-property name="chooseClassId" type="java.lang.Integer">
                <column name="ChooseClassID" />
            </key-property>
        </composite-id>
            <property name="usersId" type="java.lang.Integer">
                <column name="UsersID" />
            </property>
            <property name="usersName" type="java.lang.String">
                <column name="UsersName" />
            </property>
            <property name="password" type="java.lang.String">
                <column name="Password" />
            </property>
            <property name="isStudent" type="java.lang.Short">
                <column name="IsStudent" />
            </property>
            <property name="email" type="java.lang.String">
                <column name="Email" />
            </property>
            <property name="wechatId" type="java.lang.String">
                <column name="WechatID" />
            </property>
            <property name="weiboId" type="java.lang.String">
                <column name="WeiboID" />
            </property>
            <property name="imageId" type="java.lang.String">
                <column name="ImageID" />
            </property>
            <property name="phoneNumber" type="java.lang.String">
                <column name="PhoneNumber" />
            </property>
            <property name="name" type="java.lang.String">
                <column name="Name" />
            </property>
            <property name="studentId" type="java.lang.Integer">
                <column name="StudentID" />
            </property>
            <property name="classId" type="java.lang.Integer">
                <column name="ClassID" />
            </property>
    </class>
</hibernate-mapping>
